{"variants":[{"traits":[{"interfaceLanguage":"swift"}],"paths":["\/documentation\/volt\/developertoolssupport\/imageresource"]}],"sections":[],"hierarchy":{"paths":[["doc:\/\/com.KCDev.Volt\/documentation\/Volt","doc:\/\/com.KCDev.Volt\/documentation\/Volt\/DeveloperToolsSupport"]]},"topicSections":[{"title":"Type Properties","identifiers":["doc:\/\/com.KCDev.Volt\/documentation\/Volt\/DeveloperToolsSupport\/ImageResource\/acsLogo","doc:\/\/com.KCDev.Volt\/documentation\/Volt\/DeveloperToolsSupport\/ImageResource\/acsLogoWhite","doc:\/\/com.KCDev.Volt\/documentation\/Volt\/DeveloperToolsSupport\/ImageResource\/apprentice","doc:\/\/com.KCDev.Volt\/documentation\/Volt\/DeveloperToolsSupport\/ImageResource\/automation","doc:\/\/com.KCDev.Volt\/documentation\/Volt\/DeveloperToolsSupport\/ImageResource\/avatarDefault","doc:\/\/com.KCDev.Volt\/documentation\/Volt\/DeveloperToolsSupport\/ImageResource\/background1","doc:\/\/com.KCDev.Volt\/documentation\/Volt\/DeveloperToolsSupport\/ImageResource\/background10","doc:\/\/com.KCDev.Volt\/documentation\/Volt\/DeveloperToolsSupport\/ImageResource\/background2","doc:\/\/com.KCDev.Volt\/documentation\/Volt\/DeveloperToolsSupport\/ImageResource\/background3","doc:\/\/com.KCDev.Volt\/documentation\/Volt\/DeveloperToolsSupport\/ImageResource\/background4","doc:\/\/com.KCDev.Volt\/documentation\/Volt\/DeveloperToolsSupport\/ImageResource\/background5","doc:\/\/com.KCDev.Volt\/documentation\/Volt\/DeveloperToolsSupport\/ImageResource\/background6","doc:\/\/com.KCDev.Volt\/documentation\/Volt\/DeveloperToolsSupport\/ImageResource\/background7","doc:\/\/com.KCDev.Volt\/documentation\/Volt\/DeveloperToolsSupport\/ImageResource\/background8","doc:\/\/com.KCDev.Volt\/documentation\/Volt\/DeveloperToolsSupport\/ImageResource\/background9","doc:\/\/com.KCDev.Volt\/documentation\/Volt\/DeveloperToolsSupport\/ImageResource\/blacksmith","doc:\/\/com.KCDev.Volt\/documentation\/Volt\/DeveloperToolsSupport\/ImageResource\/blob1","doc:\/\/com.KCDev.Volt\/documentation\/Volt\/DeveloperToolsSupport\/ImageResource\/blueRidgePowerLogo","doc:\/\/com.KCDev.Volt\/documentation\/Volt\/DeveloperToolsSupport\/ImageResource\/blueRidgePowerLogoWhite","doc:\/\/com.KCDev.Volt\/documentation\/Volt\/DeveloperToolsSupport\/ImageResource\/capitolHill","doc:\/\/com.KCDev.Volt\/documentation\/Volt\/DeveloperToolsSupport\/ImageResource\/cjrRenewablesLogo","doc:\/\/com.KCDev.Volt\/documentation\/Volt\/DeveloperToolsSupport\/ImageResource\/depcomLogo","doc:\/\/com.KCDev.Volt\/documentation\/Volt\/DeveloperToolsSupport\/ImageResource\/digitalPlatform","doc:\/\/com.KCDev.Volt\/documentation\/Volt\/DeveloperToolsSupport\/ImageResource\/economy","doc:\/\/com.KCDev.Volt\/documentation\/Volt\/DeveloperToolsSupport\/ImageResource\/global","doc:\/\/com.KCDev.Volt\/documentation\/Volt\/DeveloperToolsSupport\/ImageResource\/gloss1","doc:\/\/com.KCDev.Volt\/documentation\/Volt\/DeveloperToolsSupport\/ImageResource\/gloss2","doc:\/\/com.KCDev.Volt\/documentation\/Volt\/DeveloperToolsSupport\/ImageResource\/illustration1","doc:\/\/com.KCDev.Volt\/documentation\/Volt\/DeveloperToolsSupport\/ImageResource\/illustration10","doc:\/\/com.KCDev.Volt\/documentation\/Volt\/DeveloperToolsSupport\/ImageResource\/illustration11","doc:\/\/com.KCDev.Volt\/documentation\/Volt\/DeveloperToolsSupport\/ImageResource\/illustration2","doc:\/\/com.KCDev.Volt\/documentation\/Volt\/DeveloperToolsSupport\/ImageResource\/illustration3","doc:\/\/com.KCDev.Volt\/documentation\/Volt\/DeveloperToolsSupport\/ImageResource\/illustration4","doc:\/\/com.KCDev.Volt\/documentation\/Volt\/DeveloperToolsSupport\/ImageResource\/illustration5","doc:\/\/com.KCDev.Volt\/documentation\/Volt\/DeveloperToolsSupport\/ImageResource\/illustration6","doc:\/\/com.KCDev.Volt\/documentation\/Volt\/DeveloperToolsSupport\/ImageResource\/illustration7","doc:\/\/com.KCDev.Volt\/documentation\/Volt\/DeveloperToolsSupport\/ImageResource\/illustration8","doc:\/\/com.KCDev.Volt\/documentation\/Volt\/DeveloperToolsSupport\/ImageResource\/illustration9","doc:\/\/com.KCDev.Volt\/documentation\/Volt\/DeveloperToolsSupport\/ImageResource\/inviteTeamMemberIcon","doc:\/\/com.KCDev.Volt\/documentation\/Volt\/DeveloperToolsSupport\/ImageResource\/launchScreen","doc:\/\/com.KCDev.Volt\/documentation\/Volt\/DeveloperToolsSupport\/ImageResource\/logo1","doc:\/\/com.KCDev.Volt\/documentation\/Volt\/DeveloperToolsSupport\/ImageResource\/logo2","doc:\/\/com.KCDev.Volt\/documentation\/Volt\/DeveloperToolsSupport\/ImageResource\/logo3","doc:\/\/com.KCDev.Volt\/documentation\/Volt\/DeveloperToolsSupport\/ImageResource\/logo4","doc:\/\/com.KCDev.Volt\/documentation\/Volt\/DeveloperToolsSupport\/ImageResource\/logoApple","doc:\/\/com.KCDev.Volt\/documentation\/Volt\/DeveloperToolsSupport\/ImageResource\/logoEmail","doc:\/\/com.KCDev.Volt\/documentation\/Volt\/DeveloperToolsSupport\/ImageResource\/logoGoogle","doc:\/\/com.KCDev.Volt\/documentation\/Volt\/DeveloperToolsSupport\/ImageResource\/logoGoogleOLD","doc:\/\/com.KCDev.Volt\/documentation\/Volt\/DeveloperToolsSupport\/ImageResource\/logoGooglePDF","doc:\/\/com.KCDev.Volt\/documentation\/Volt\/DeveloperToolsSupport\/ImageResource\/mortensonLogo","doc:\/\/com.KCDev.Volt\/documentation\/Volt\/DeveloperToolsSupport\/ImageResource\/mortensonLogoWhite","doc:\/\/com.KCDev.Volt\/documentation\/Volt\/DeveloperToolsSupport\/ImageResource\/newEnrollmentIcon","doc:\/\/com.KCDev.Volt\/documentation\/Volt\/DeveloperToolsSupport\/ImageResource\/partnership","doc:\/\/com.KCDev.Volt\/documentation\/Volt\/DeveloperToolsSupport\/ImageResource\/primorisLogo","doc:\/\/com.KCDev.Volt\/documentation\/Volt\/DeveloperToolsSupport\/ImageResource\/primorisLogoBasic","doc:\/\/com.KCDev.Volt\/documentation\/Volt\/DeveloperToolsSupport\/ImageResource\/primorisLogoWhite","doc:\/\/com.KCDev.Volt\/documentation\/Volt\/DeveloperToolsSupport\/ImageResource\/primorisLogoWhiteSmall","doc:\/\/com.KCDev.Volt\/documentation\/Volt\/DeveloperToolsSupport\/ImageResource\/renewables","doc:\/\/com.KCDev.Volt\/documentation\/Volt\/DeveloperToolsSupport\/ImageResource\/resLogo","doc:\/\/com.KCDev.Volt\/documentation\/Volt\/DeveloperToolsSupport\/ImageResource\/solvLogo","doc:\/\/com.KCDev.Volt\/documentation\/Volt\/DeveloperToolsSupport\/ImageResource\/spark","doc:\/\/com.KCDev.Volt\/documentation\/Volt\/DeveloperToolsSupport\/ImageResource\/sponsor","doc:\/\/com.KCDev.Volt\/documentation\/Volt\/DeveloperToolsSupport\/ImageResource\/success","doc:\/\/com.KCDev.Volt\/documentation\/Volt\/DeveloperToolsSupport\/ImageResource\/sustainable","doc:\/\/com.KCDev.Volt\/documentation\/Volt\/DeveloperToolsSupport\/ImageResource\/syncDataIcon","doc:\/\/com.KCDev.Volt\/documentation\/Volt\/DeveloperToolsSupport\/ImageResource\/technologyApprenticeship","doc:\/\/com.KCDev.Volt\/documentation\/Volt\/DeveloperToolsSupport\/ImageResource\/viewDocuSignIcon","doc:\/\/com.KCDev.Volt\/documentation\/Volt\/DeveloperToolsSupport\/ImageResource\/voltLogo","doc:\/\/com.KCDev.Volt\/documentation\/Volt\/DeveloperToolsSupport\/ImageResource\/wallpaper3","doc:\/\/com.KCDev.Volt\/documentation\/Volt\/DeveloperToolsSupport\/ImageResource\/waves1","doc:\/\/com.KCDev.Volt\/documentation\/Volt\/DeveloperToolsSupport\/ImageResource\/waves2","doc:\/\/com.KCDev.Volt\/documentation\/Volt\/DeveloperToolsSupport\/ImageResource\/whcLogo","doc:\/\/com.KCDev.Volt\/documentation\/Volt\/DeveloperToolsSupport\/ImageResource\/workforce"]}],"kind":"symbol","schemaVersion":{"patch":0,"major":0,"minor":3},"metadata":{"navigatorTitle":[{"kind":"identifier","text":"ImageResource"}],"symbolKind":"extension","role":"symbol","roleHeading":"Extended Structure","modules":[{"relatedModules":["DeveloperToolsSupport"],"name":"Volt"}],"extendedModule":"DeveloperToolsSupport","externalID":"s:e:s:21DeveloperToolsSupport13ImageResourceV4VoltE7acsLogoACvpZ","fragments":[{"text":"extension","kind":"keyword"},{"text":" ","kind":"text"},{"text":"DeveloperToolsSupport","kind":"identifier"},{"text":".","kind":"text"},{"text":"ImageResource","kind":"identifier","preciseIdentifier":"s:21DeveloperToolsSupport13ImageResourceV"}],"title":"ImageResource"},"primaryContentSections":[{"kind":"declarations","declarations":[{"tokens":[{"kind":"keyword","text":"extension"},{"kind":"text","text":" "},{"text":"DeveloperToolsSupport","kind":"identifier"},{"kind":"text","text":"."},{"kind":"typeIdentifier","text":"ImageResource","preciseIdentifier":"s:21DeveloperToolsSupport13ImageResourceV"}],"platforms":["iOS"],"languages":["swift"]}]}],"identifier":{"interfaceLanguage":"swift","url":"doc:\/\/com.KCDev.Volt\/documentation\/Volt\/DeveloperToolsSupport\/ImageResource"},"references":{"doc://com.KCDev.Volt/documentation/Volt/DeveloperToolsSupport/ImageResource/illustration6":{"title":"illustration6","type":"topic","role":"symbol","fragments":[{"kind":"keyword","text":"static"},{"kind":"text","text":" "},{"kind":"keyword","text":"let"},{"kind":"text","text":" "},{"text":"illustration6","kind":"identifier"},{"text":": ","kind":"text"},{"text":"ImageResource","kind":"typeIdentifier","preciseIdentifier":"s:21DeveloperToolsSupport13ImageResourceV"}],"kind":"symbol","url":"\/documentation\/volt\/developertoolssupport\/imageresource\/illustration6","abstract":[{"text":"The “Illustration 6” asset catalog image resource.","type":"text"}],"identifier":"doc:\/\/com.KCDev.Volt\/documentation\/Volt\/DeveloperToolsSupport\/ImageResource\/illustration6"},"doc://com.KCDev.Volt/documentation/Volt/DeveloperToolsSupport/ImageResource/background8":{"url":"\/documentation\/volt\/developertoolssupport\/imageresource\/background8","abstract":[{"text":"The “Background 8” asset catalog image resource.","type":"text"}],"kind":"symbol","type":"topic","identifier":"doc:\/\/com.KCDev.Volt\/documentation\/Volt\/DeveloperToolsSupport\/ImageResource\/background8","role":"symbol","title":"background8","fragments":[{"text":"static","kind":"keyword"},{"text":" ","kind":"text"},{"kind":"keyword","text":"let"},{"kind":"text","text":" "},{"kind":"identifier","text":"background8"},{"text":": ","kind":"text"},{"preciseIdentifier":"s:21DeveloperToolsSupport13ImageResourceV","text":"ImageResource","kind":"typeIdentifier"}]},"doc://com.KCDev.Volt/documentation/Volt/DeveloperToolsSupport/ImageResource/primorisLogoWhiteSmall":{"identifier":"doc:\/\/com.KCDev.Volt\/documentation\/Volt\/DeveloperToolsSupport\/ImageResource\/primorisLogoWhiteSmall","title":"primorisLogoWhiteSmall","abstract":[{"text":"The “Primoris Logo White Small” asset catalog image resource.","type":"text"}],"role":"symbol","type":"topic","url":"\/documentation\/volt\/developertoolssupport\/imageresource\/primorislogowhitesmall","fragments":[{"kind":"keyword","text":"static"},{"kind":"text","text":" "},{"text":"let","kind":"keyword"},{"text":" ","kind":"text"},{"kind":"identifier","text":"primorisLogoWhiteSmall"},{"text":": ","kind":"text"},{"kind":"typeIdentifier","text":"ImageResource","preciseIdentifier":"s:21DeveloperToolsSupport13ImageResourceV"}],"kind":"symbol"},"doc://com.KCDev.Volt/documentation/Volt/DeveloperToolsSupport/ImageResource/illustration2":{"url":"\/documentation\/volt\/developertoolssupport\/imageresource\/illustration2","identifier":"doc:\/\/com.KCDev.Volt\/documentation\/Volt\/DeveloperToolsSupport\/ImageResource\/illustration2","title":"illustration2","fragments":[{"kind":"keyword","text":"static"},{"kind":"text","text":" "},{"text":"let","kind":"keyword"},{"kind":"text","text":" "},{"text":"illustration2","kind":"identifier"},{"text":": ","kind":"text"},{"text":"ImageResource","preciseIdentifier":"s:21DeveloperToolsSupport13ImageResourceV","kind":"typeIdentifier"}],"kind":"symbol","role":"symbol","abstract":[{"type":"text","text":"The “Illustration 2” asset catalog image resource."}],"type":"topic"},"doc://com.KCDev.Volt/documentation/Volt/DeveloperToolsSupport/ImageResource/background4":{"identifier":"doc:\/\/com.KCDev.Volt\/documentation\/Volt\/DeveloperToolsSupport\/ImageResource\/background4","kind":"symbol","role":"symbol","fragments":[{"text":"static","kind":"keyword"},{"text":" ","kind":"text"},{"kind":"keyword","text":"let"},{"text":" ","kind":"text"},{"kind":"identifier","text":"background4"},{"kind":"text","text":": "},{"preciseIdentifier":"s:21DeveloperToolsSupport13ImageResourceV","kind":"typeIdentifier","text":"ImageResource"}],"title":"background4","type":"topic","url":"\/documentation\/volt\/developertoolssupport\/imageresource\/background4","abstract":[{"type":"text","text":"The “Background 4” asset catalog image resource."}]},"doc://com.KCDev.Volt/documentation/Volt/DeveloperToolsSupport/ImageResource/inviteTeamMemberIcon":{"url":"\/documentation\/volt\/developertoolssupport\/imageresource\/inviteteammembericon","title":"inviteTeamMemberIcon","type":"topic","identifier":"doc:\/\/com.KCDev.Volt\/documentation\/Volt\/DeveloperToolsSupport\/ImageResource\/inviteTeamMemberIcon","abstract":[{"type":"text","text":"The “Invite Team Member Icon” asset catalog image resource."}],"kind":"symbol","role":"symbol","fragments":[{"text":"static","kind":"keyword"},{"kind":"text","text":" "},{"text":"let","kind":"keyword"},{"text":" ","kind":"text"},{"kind":"identifier","text":"inviteTeamMemberIcon"},{"text":": ","kind":"text"},{"kind":"typeIdentifier","preciseIdentifier":"s:21DeveloperToolsSupport13ImageResourceV","text":"ImageResource"}]},"doc://com.KCDev.Volt/documentation/Volt/DeveloperToolsSupport/ImageResource/avatarDefault":{"abstract":[{"type":"text","text":"The “Avatar Default” asset catalog image resource."}],"title":"avatarDefault","identifier":"doc:\/\/com.KCDev.Volt\/documentation\/Volt\/DeveloperToolsSupport\/ImageResource\/avatarDefault","role":"symbol","kind":"symbol","url":"\/documentation\/volt\/developertoolssupport\/imageresource\/avatardefault","fragments":[{"kind":"keyword","text":"static"},{"text":" ","kind":"text"},{"kind":"keyword","text":"let"},{"text":" ","kind":"text"},{"text":"avatarDefault","kind":"identifier"},{"text":": ","kind":"text"},{"text":"ImageResource","kind":"typeIdentifier","preciseIdentifier":"s:21DeveloperToolsSupport13ImageResourceV"}],"type":"topic"},"doc://com.KCDev.Volt/documentation/Volt/DeveloperToolsSupport/ImageResource/depcomLogo":{"kind":"symbol","abstract":[{"type":"text","text":"The “Depcom Logo” asset catalog image resource."}],"url":"\/documentation\/volt\/developertoolssupport\/imageresource\/depcomlogo","type":"topic","title":"depcomLogo","identifier":"doc:\/\/com.KCDev.Volt\/documentation\/Volt\/DeveloperToolsSupport\/ImageResource\/depcomLogo","role":"symbol","fragments":[{"text":"static","kind":"keyword"},{"text":" ","kind":"text"},{"kind":"keyword","text":"let"},{"text":" ","kind":"text"},{"text":"depcomLogo","kind":"identifier"},{"kind":"text","text":": "},{"preciseIdentifier":"s:21DeveloperToolsSupport13ImageResourceV","kind":"typeIdentifier","text":"ImageResource"}]},"doc://com.KCDev.Volt/documentation/Volt/DeveloperToolsSupport/ImageResource/mortensonLogoWhite":{"identifier":"doc:\/\/com.KCDev.Volt\/documentation\/Volt\/DeveloperToolsSupport\/ImageResource\/mortensonLogoWhite","fragments":[{"kind":"keyword","text":"static"},{"text":" ","kind":"text"},{"text":"let","kind":"keyword"},{"kind":"text","text":" "},{"kind":"identifier","text":"mortensonLogoWhite"},{"kind":"text","text":": "},{"text":"ImageResource","kind":"typeIdentifier","preciseIdentifier":"s:21DeveloperToolsSupport13ImageResourceV"}],"role":"symbol","title":"mortensonLogoWhite","abstract":[{"type":"text","text":"The “Mortenson Logo White” asset catalog image resource."}],"type":"topic","kind":"symbol","url":"\/documentation\/volt\/developertoolssupport\/imageresource\/mortensonlogowhite"},"doc://com.KCDev.Volt/documentation/Volt/DeveloperToolsSupport/ImageResource":{"kind":"symbol","abstract":[],"url":"\/documentation\/volt\/developertoolssupport\/imageresource","type":"topic","title":"ImageResource","identifier":"doc:\/\/com.KCDev.Volt\/documentation\/Volt\/DeveloperToolsSupport\/ImageResource","role":"symbol","fragments":[{"kind":"keyword","text":"extension"},{"kind":"text","text":" "},{"text":"DeveloperToolsSupport","kind":"identifier"},{"text":".","kind":"text"},{"preciseIdentifier":"s:21DeveloperToolsSupport13ImageResourceV","kind":"identifier","text":"ImageResource"}],"navigatorTitle":[{"text":"ImageResource","kind":"identifier"}]},"doc://com.KCDev.Volt/documentation/Volt/DeveloperToolsSupport/ImageResource/background3":{"role":"symbol","fragments":[{"text":"static","kind":"keyword"},{"kind":"text","text":" "},{"kind":"keyword","text":"let"},{"kind":"text","text":" "},{"kind":"identifier","text":"background3"},{"text":": ","kind":"text"},{"preciseIdentifier":"s:21DeveloperToolsSupport13ImageResourceV","text":"ImageResource","kind":"typeIdentifier"}],"title":"background3","identifier":"doc:\/\/com.KCDev.Volt\/documentation\/Volt\/DeveloperToolsSupport\/ImageResource\/background3","kind":"symbol","url":"\/documentation\/volt\/developertoolssupport\/imageresource\/background3","type":"topic","abstract":[{"type":"text","text":"The “Background 3” asset catalog image resource."}]},"doc://com.KCDev.Volt/documentation/Volt/DeveloperToolsSupport/ImageResource/success":{"fragments":[{"text":"static","kind":"keyword"},{"text":" ","kind":"text"},{"kind":"keyword","text":"let"},{"kind":"text","text":" "},{"kind":"identifier","text":"success"},{"text":": ","kind":"text"},{"kind":"typeIdentifier","preciseIdentifier":"s:21DeveloperToolsSupport13ImageResourceV","text":"ImageResource"}],"abstract":[{"text":"The “Success” asset catalog image resource.","type":"text"}],"url":"\/documentation\/volt\/developertoolssupport\/imageresource\/success","title":"success","kind":"symbol","identifier":"doc:\/\/com.KCDev.Volt\/documentation\/Volt\/DeveloperToolsSupport\/ImageResource\/success","type":"topic","role":"symbol"},"doc://com.KCDev.Volt/documentation/Volt/DeveloperToolsSupport/ImageResource/launchScreen":{"title":"launchScreen","fragments":[{"kind":"keyword","text":"static"},{"text":" ","kind":"text"},{"text":"let","kind":"keyword"},{"text":" ","kind":"text"},{"text":"launchScreen","kind":"identifier"},{"kind":"text","text":": "},{"kind":"typeIdentifier","preciseIdentifier":"s:21DeveloperToolsSupport13ImageResourceV","text":"ImageResource"}],"type":"topic","url":"\/documentation\/volt\/developertoolssupport\/imageresource\/launchscreen","kind":"symbol","role":"symbol","abstract":[{"type":"text","text":"The “LaunchScreen” asset catalog image resource."}],"identifier":"doc:\/\/com.KCDev.Volt\/documentation\/Volt\/DeveloperToolsSupport\/ImageResource\/launchScreen"},"doc://com.KCDev.Volt/documentation/Volt/DeveloperToolsSupport/ImageResource/illustration5":{"role":"symbol","type":"topic","fragments":[{"text":"static","kind":"keyword"},{"kind":"text","text":" "},{"kind":"keyword","text":"let"},{"text":" ","kind":"text"},{"text":"illustration5","kind":"identifier"},{"kind":"text","text":": "},{"text":"ImageResource","kind":"typeIdentifier","preciseIdentifier":"s:21DeveloperToolsSupport13ImageResourceV"}],"title":"illustration5","url":"\/documentation\/volt\/developertoolssupport\/imageresource\/illustration5","abstract":[{"type":"text","text":"The “Illustration 5” asset catalog image resource."}],"identifier":"doc:\/\/com.KCDev.Volt\/documentation\/Volt\/DeveloperToolsSupport\/ImageResource\/illustration5","kind":"symbol"},"doc://com.KCDev.Volt/documentation/Volt/DeveloperToolsSupport/ImageResource/logoGoogleOLD":{"url":"\/documentation\/volt\/developertoolssupport\/imageresource\/logogoogleold","kind":"symbol","abstract":[{"text":"The “Logo Google OLD” asset catalog image resource.","type":"text"}],"identifier":"doc:\/\/com.KCDev.Volt\/documentation\/Volt\/DeveloperToolsSupport\/ImageResource\/logoGoogleOLD","fragments":[{"text":"static","kind":"keyword"},{"kind":"text","text":" "},{"text":"let","kind":"keyword"},{"kind":"text","text":" "},{"kind":"identifier","text":"logoGoogleOLD"},{"kind":"text","text":": "},{"text":"ImageResource","kind":"typeIdentifier","preciseIdentifier":"s:21DeveloperToolsSupport13ImageResourceV"}],"title":"logoGoogleOLD","type":"topic","role":"symbol"},"doc://com.KCDev.Volt/documentation/Volt/DeveloperToolsSupport/ImageResource/illustration9":{"kind":"symbol","identifier":"doc:\/\/com.KCDev.Volt\/documentation\/Volt\/DeveloperToolsSupport\/ImageResource\/illustration9","url":"\/documentation\/volt\/developertoolssupport\/imageresource\/illustration9","role":"symbol","type":"topic","fragments":[{"kind":"keyword","text":"static"},{"text":" ","kind":"text"},{"text":"let","kind":"keyword"},{"text":" ","kind":"text"},{"kind":"identifier","text":"illustration9"},{"text":": ","kind":"text"},{"text":"ImageResource","preciseIdentifier":"s:21DeveloperToolsSupport13ImageResourceV","kind":"typeIdentifier"}],"abstract":[{"type":"text","text":"The “Illustration 9” asset catalog image resource."}],"title":"illustration9"},"doc://com.KCDev.Volt/documentation/Volt/DeveloperToolsSupport/ImageResource/whcLogo":{"url":"\/documentation\/volt\/developertoolssupport\/imageresource\/whclogo","role":"symbol","identifier":"doc:\/\/com.KCDev.Volt\/documentation\/Volt\/DeveloperToolsSupport\/ImageResource\/whcLogo","abstract":[{"text":"The “WHC Logo” asset catalog image resource.","type":"text"}],"fragments":[{"kind":"keyword","text":"static"},{"kind":"text","text":" "},{"kind":"keyword","text":"let"},{"text":" ","kind":"text"},{"text":"whcLogo","kind":"identifier"},{"text":": ","kind":"text"},{"kind":"typeIdentifier","preciseIdentifier":"s:21DeveloperToolsSupport13ImageResourceV","text":"ImageResource"}],"type":"topic","title":"whcLogo","kind":"symbol"},"doc://com.KCDev.Volt/documentation/Volt/DeveloperToolsSupport/ImageResource/waves1":{"role":"symbol","fragments":[{"text":"static","kind":"keyword"},{"text":" ","kind":"text"},{"kind":"keyword","text":"let"},{"kind":"text","text":" "},{"kind":"identifier","text":"waves1"},{"kind":"text","text":": "},{"text":"ImageResource","kind":"typeIdentifier","preciseIdentifier":"s:21DeveloperToolsSupport13ImageResourceV"}],"title":"waves1","kind":"symbol","identifier":"doc:\/\/com.KCDev.Volt\/documentation\/Volt\/DeveloperToolsSupport\/ImageResource\/waves1","url":"\/documentation\/volt\/developertoolssupport\/imageresource\/waves1","type":"topic","abstract":[{"type":"text","text":"The “Waves 1” asset catalog image resource."}]},"doc://com.KCDev.Volt/documentation/Volt/DeveloperToolsSupport/ImageResource/resLogo":{"role":"symbol","fragments":[{"kind":"keyword","text":"static"},{"kind":"text","text":" "},{"kind":"keyword","text":"let"},{"kind":"text","text":" "},{"text":"resLogo","kind":"identifier"},{"kind":"text","text":": "},{"preciseIdentifier":"s:21DeveloperToolsSupport13ImageResourceV","text":"ImageResource","kind":"typeIdentifier"}],"kind":"symbol","title":"resLogo","url":"\/documentation\/volt\/developertoolssupport\/imageresource\/reslogo","identifier":"doc:\/\/com.KCDev.Volt\/documentation\/Volt\/DeveloperToolsSupport\/ImageResource\/resLogo","type":"topic","abstract":[{"type":"text","text":"The “RES Logo” asset catalog image resource."}]},"doc://com.KCDev.Volt/documentation/Volt/DeveloperToolsSupport/ImageResource/voltLogo":{"identifier":"doc:\/\/com.KCDev.Volt\/documentation\/Volt\/DeveloperToolsSupport\/ImageResource\/voltLogo","title":"voltLogo","url":"\/documentation\/volt\/developertoolssupport\/imageresource\/voltlogo","role":"symbol","abstract":[{"type":"text","text":"The “Volt Logo” asset catalog image resource."}],"kind":"symbol","type":"topic","fragments":[{"kind":"keyword","text":"static"},{"kind":"text","text":" "},{"kind":"keyword","text":"let"},{"kind":"text","text":" "},{"text":"voltLogo","kind":"identifier"},{"text":": ","kind":"text"},{"preciseIdentifier":"s:21DeveloperToolsSupport13ImageResourceV","kind":"typeIdentifier","text":"ImageResource"}]},"doc://com.KCDev.Volt/documentation/Volt/DeveloperToolsSupport/ImageResource/illustration8":{"type":"topic","kind":"symbol","fragments":[{"text":"static","kind":"keyword"},{"kind":"text","text":" "},{"kind":"keyword","text":"let"},{"kind":"text","text":" "},{"kind":"identifier","text":"illustration8"},{"kind":"text","text":": "},{"preciseIdentifier":"s:21DeveloperToolsSupport13ImageResourceV","text":"ImageResource","kind":"typeIdentifier"}],"title":"illustration8","identifier":"doc:\/\/com.KCDev.Volt\/documentation\/Volt\/DeveloperToolsSupport\/ImageResource\/illustration8","role":"symbol","abstract":[{"text":"The “Illustration 8” asset catalog image resource.","type":"text"}],"url":"\/documentation\/volt\/developertoolssupport\/imageresource\/illustration8"},"doc://com.KCDev.Volt/documentation/Volt/DeveloperToolsSupport/ImageResource/background10":{"role":"symbol","url":"\/documentation\/volt\/developertoolssupport\/imageresource\/background10","kind":"symbol","title":"background10","abstract":[{"type":"text","text":"The “Background 10” asset catalog image resource."}],"fragments":[{"kind":"keyword","text":"static"},{"kind":"text","text":" "},{"kind":"keyword","text":"let"},{"text":" ","kind":"text"},{"text":"background10","kind":"identifier"},{"text":": ","kind":"text"},{"preciseIdentifier":"s:21DeveloperToolsSupport13ImageResourceV","kind":"typeIdentifier","text":"ImageResource"}],"type":"topic","identifier":"doc:\/\/com.KCDev.Volt\/documentation\/Volt\/DeveloperToolsSupport\/ImageResource\/background10"},"doc://com.KCDev.Volt/documentation/Volt":{"title":"Volt","url":"\/documentation\/volt","type":"topic","abstract":[{"text":"Volt is a comprehensive platform designed to manage various aspects of apprenticeship and training programs. It integrates several functionalities, from user management to course handling, making it an all-encompassing solution for educational and professional development needs.","type":"text"}],"kind":"symbol","identifier":"doc:\/\/com.KCDev.Volt\/documentation\/Volt","role":"collection"},"doc://com.KCDev.Volt/documentation/Volt/DeveloperToolsSupport/ImageResource/sustainable":{"role":"symbol","url":"\/documentation\/volt\/developertoolssupport\/imageresource\/sustainable","kind":"symbol","type":"topic","title":"sustainable","fragments":[{"text":"static","kind":"keyword"},{"kind":"text","text":" "},{"kind":"keyword","text":"let"},{"text":" ","kind":"text"},{"kind":"identifier","text":"sustainable"},{"text":": ","kind":"text"},{"preciseIdentifier":"s:21DeveloperToolsSupport13ImageResourceV","text":"ImageResource","kind":"typeIdentifier"}],"identifier":"doc:\/\/com.KCDev.Volt\/documentation\/Volt\/DeveloperToolsSupport\/ImageResource\/sustainable","abstract":[{"type":"text","text":"The “Sustainable” asset catalog image resource."}]},"doc://com.KCDev.Volt/documentation/Volt/DeveloperToolsSupport/ImageResource/illustration3":{"type":"topic","identifier":"doc:\/\/com.KCDev.Volt\/documentation\/Volt\/DeveloperToolsSupport\/ImageResource\/illustration3","abstract":[{"text":"The “Illustration 3” asset catalog image resource.","type":"text"}],"kind":"symbol","role":"symbol","fragments":[{"kind":"keyword","text":"static"},{"kind":"text","text":" "},{"kind":"keyword","text":"let"},{"kind":"text","text":" "},{"kind":"identifier","text":"illustration3"},{"text":": ","kind":"text"},{"kind":"typeIdentifier","text":"ImageResource","preciseIdentifier":"s:21DeveloperToolsSupport13ImageResourceV"}],"title":"illustration3","url":"\/documentation\/volt\/developertoolssupport\/imageresource\/illustration3"},"doc://com.KCDev.Volt/documentation/Volt/DeveloperToolsSupport/ImageResource/mortensonLogo":{"kind":"symbol","identifier":"doc:\/\/com.KCDev.Volt\/documentation\/Volt\/DeveloperToolsSupport\/ImageResource\/mortensonLogo","title":"mortensonLogo","role":"symbol","fragments":[{"kind":"keyword","text":"static"},{"kind":"text","text":" "},{"kind":"keyword","text":"let"},{"kind":"text","text":" "},{"kind":"identifier","text":"mortensonLogo"},{"kind":"text","text":": "},{"text":"ImageResource","preciseIdentifier":"s:21DeveloperToolsSupport13ImageResourceV","kind":"typeIdentifier"}],"type":"topic","url":"\/documentation\/volt\/developertoolssupport\/imageresource\/mortensonlogo","abstract":[{"text":"The “Mortenson Logo” asset catalog image resource.","type":"text"}]},"doc://com.KCDev.Volt/documentation/Volt/DeveloperToolsSupport/ImageResource/workforce":{"type":"topic","identifier":"doc:\/\/com.KCDev.Volt\/documentation\/Volt\/DeveloperToolsSupport\/ImageResource\/workforce","role":"symbol","fragments":[{"kind":"keyword","text":"static"},{"kind":"text","text":" "},{"text":"let","kind":"keyword"},{"text":" ","kind":"text"},{"kind":"identifier","text":"workforce"},{"text":": ","kind":"text"},{"preciseIdentifier":"s:21DeveloperToolsSupport13ImageResourceV","kind":"typeIdentifier","text":"ImageResource"}],"kind":"symbol","abstract":[{"type":"text","text":"The “Workforce” asset catalog image resource."}],"title":"workforce","url":"\/documentation\/volt\/developertoolssupport\/imageresource\/workforce"},"doc://com.KCDev.Volt/documentation/Volt/DeveloperToolsSupport/ImageResource/illustration10":{"role":"symbol","url":"\/documentation\/volt\/developertoolssupport\/imageresource\/illustration10","title":"illustration10","type":"topic","abstract":[{"type":"text","text":"The “Illustration 10” asset catalog image resource."}],"identifier":"doc:\/\/com.KCDev.Volt\/documentation\/Volt\/DeveloperToolsSupport\/ImageResource\/illustration10","fragments":[{"text":"static","kind":"keyword"},{"text":" ","kind":"text"},{"text":"let","kind":"keyword"},{"text":" ","kind":"text"},{"kind":"identifier","text":"illustration10"},{"text":": ","kind":"text"},{"preciseIdentifier":"s:21DeveloperToolsSupport13ImageResourceV","kind":"typeIdentifier","text":"ImageResource"}],"kind":"symbol"},"doc://com.KCDev.Volt/documentation/Volt/DeveloperToolsSupport/ImageResource/wallpaper3":{"abstract":[{"text":"The “Wallpaper 3” asset catalog image resource.","type":"text"}],"type":"topic","fragments":[{"kind":"keyword","text":"static"},{"text":" ","kind":"text"},{"text":"let","kind":"keyword"},{"kind":"text","text":" "},{"text":"wallpaper3","kind":"identifier"},{"text":": ","kind":"text"},{"kind":"typeIdentifier","text":"ImageResource","preciseIdentifier":"s:21DeveloperToolsSupport13ImageResourceV"}],"kind":"symbol","role":"symbol","title":"wallpaper3","identifier":"doc:\/\/com.KCDev.Volt\/documentation\/Volt\/DeveloperToolsSupport\/ImageResource\/wallpaper3","url":"\/documentation\/volt\/developertoolssupport\/imageresource\/wallpaper3"},"doc://com.KCDev.Volt/documentation/Volt/DeveloperToolsSupport/ImageResource/background5":{"title":"background5","url":"\/documentation\/volt\/developertoolssupport\/imageresource\/background5","fragments":[{"text":"static","kind":"keyword"},{"kind":"text","text":" "},{"kind":"keyword","text":"let"},{"text":" ","kind":"text"},{"kind":"identifier","text":"background5"},{"text":": ","kind":"text"},{"kind":"typeIdentifier","text":"ImageResource","preciseIdentifier":"s:21DeveloperToolsSupport13ImageResourceV"}],"identifier":"doc:\/\/com.KCDev.Volt\/documentation\/Volt\/DeveloperToolsSupport\/ImageResource\/background5","role":"symbol","kind":"symbol","type":"topic","abstract":[{"type":"text","text":"The “Background 5” asset catalog image resource."}]},"doc://com.KCDev.Volt/documentation/Volt/DeveloperToolsSupport/ImageResource/solvLogo":{"kind":"symbol","title":"solvLogo","role":"symbol","identifier":"doc:\/\/com.KCDev.Volt\/documentation\/Volt\/DeveloperToolsSupport\/ImageResource\/solvLogo","url":"\/documentation\/volt\/developertoolssupport\/imageresource\/solvlogo","type":"topic","fragments":[{"text":"static","kind":"keyword"},{"text":" ","kind":"text"},{"kind":"keyword","text":"let"},{"text":" ","kind":"text"},{"kind":"identifier","text":"solvLogo"},{"text":": ","kind":"text"},{"kind":"typeIdentifier","text":"ImageResource","preciseIdentifier":"s:21DeveloperToolsSupport13ImageResourceV"}],"abstract":[{"type":"text","text":"The “SOLV Logo” asset catalog image resource."}]},"doc://com.KCDev.Volt/documentation/Volt/DeveloperToolsSupport/ImageResource/primorisLogo":{"abstract":[{"type":"text","text":"The “Primoris Logo” asset catalog image resource."}],"title":"primorisLogo","url":"\/documentation\/volt\/developertoolssupport\/imageresource\/primorislogo","kind":"symbol","type":"topic","fragments":[{"text":"static","kind":"keyword"},{"text":" ","kind":"text"},{"kind":"keyword","text":"let"},{"text":" ","kind":"text"},{"text":"primorisLogo","kind":"identifier"},{"text":": ","kind":"text"},{"text":"ImageResource","preciseIdentifier":"s:21DeveloperToolsSupport13ImageResourceV","kind":"typeIdentifier"}],"role":"symbol","identifier":"doc:\/\/com.KCDev.Volt\/documentation\/Volt\/DeveloperToolsSupport\/ImageResource\/primorisLogo"},"doc://com.KCDev.Volt/documentation/Volt/DeveloperToolsSupport/ImageResource/illustration7":{"abstract":[{"type":"text","text":"The “Illustration 7” asset catalog image resource."}],"title":"illustration7","url":"\/documentation\/volt\/developertoolssupport\/imageresource\/illustration7","kind":"symbol","role":"symbol","type":"topic","fragments":[{"text":"static","kind":"keyword"},{"text":" ","kind":"text"},{"kind":"keyword","text":"let"},{"kind":"text","text":" "},{"text":"illustration7","kind":"identifier"},{"kind":"text","text":": "},{"preciseIdentifier":"s:21DeveloperToolsSupport13ImageResourceV","kind":"typeIdentifier","text":"ImageResource"}],"identifier":"doc:\/\/com.KCDev.Volt\/documentation\/Volt\/DeveloperToolsSupport\/ImageResource\/illustration7"},"doc://com.KCDev.Volt/documentation/Volt/DeveloperToolsSupport/ImageResource/technologyApprenticeship":{"title":"technologyApprenticeship","kind":"symbol","role":"symbol","abstract":[{"type":"text","text":"The “Technology-Apprenticeship” asset catalog image resource."}],"type":"topic","fragments":[{"text":"static","kind":"keyword"},{"kind":"text","text":" "},{"text":"let","kind":"keyword"},{"kind":"text","text":" "},{"text":"technologyApprenticeship","kind":"identifier"},{"text":": ","kind":"text"},{"preciseIdentifier":"s:21DeveloperToolsSupport13ImageResourceV","text":"ImageResource","kind":"typeIdentifier"}],"identifier":"doc:\/\/com.KCDev.Volt\/documentation\/Volt\/DeveloperToolsSupport\/ImageResource\/technologyApprenticeship","url":"\/documentation\/volt\/developertoolssupport\/imageresource\/technologyapprenticeship"},"doc://com.KCDev.Volt/documentation/Volt/DeveloperToolsSupport/ImageResource/acsLogoWhite":{"fragments":[{"text":"static","kind":"keyword"},{"text":" ","kind":"text"},{"text":"let","kind":"keyword"},{"text":" ","kind":"text"},{"kind":"identifier","text":"acsLogoWhite"},{"kind":"text","text":": "},{"kind":"typeIdentifier","text":"ImageResource","preciseIdentifier":"s:21DeveloperToolsSupport13ImageResourceV"}],"role":"symbol","url":"\/documentation\/volt\/developertoolssupport\/imageresource\/acslogowhite","type":"topic","identifier":"doc:\/\/com.KCDev.Volt\/documentation\/Volt\/DeveloperToolsSupport\/ImageResource\/acsLogoWhite","kind":"symbol","title":"acsLogoWhite","abstract":[{"type":"text","text":"The “ACS Logo White” asset catalog image resource."}]},"doc://com.KCDev.Volt/documentation/Volt/DeveloperToolsSupport/ImageResource/blueRidgePowerLogo":{"url":"\/documentation\/volt\/developertoolssupport\/imageresource\/blueridgepowerlogo","type":"topic","fragments":[{"text":"static","kind":"keyword"},{"kind":"text","text":" "},{"kind":"keyword","text":"let"},{"text":" ","kind":"text"},{"text":"blueRidgePowerLogo","kind":"identifier"},{"kind":"text","text":": "},{"kind":"typeIdentifier","preciseIdentifier":"s:21DeveloperToolsSupport13ImageResourceV","text":"ImageResource"}],"identifier":"doc:\/\/com.KCDev.Volt\/documentation\/Volt\/DeveloperToolsSupport\/ImageResource\/blueRidgePowerLogo","title":"blueRidgePowerLogo","kind":"symbol","abstract":[{"text":"The “Blue Ridge Power Logo” asset catalog image resource.","type":"text"}],"role":"symbol"},"doc://com.KCDev.Volt/documentation/Volt/DeveloperToolsSupport/ImageResource/blueRidgePowerLogoWhite":{"role":"symbol","type":"topic","url":"\/documentation\/volt\/developertoolssupport\/imageresource\/blueridgepowerlogowhite","identifier":"doc:\/\/com.KCDev.Volt\/documentation\/Volt\/DeveloperToolsSupport\/ImageResource\/blueRidgePowerLogoWhite","fragments":[{"kind":"keyword","text":"static"},{"text":" ","kind":"text"},{"kind":"keyword","text":"let"},{"text":" ","kind":"text"},{"text":"blueRidgePowerLogoWhite","kind":"identifier"},{"text":": ","kind":"text"},{"kind":"typeIdentifier","text":"ImageResource","preciseIdentifier":"s:21DeveloperToolsSupport13ImageResourceV"}],"kind":"symbol","abstract":[{"type":"text","text":"The “Blue Ridge Power Logo White” asset catalog image resource."}],"title":"blueRidgePowerLogoWhite"},"doc://com.KCDev.Volt/documentation/Volt/DeveloperToolsSupport/ImageResource/partnership":{"fragments":[{"text":"static","kind":"keyword"},{"kind":"text","text":" "},{"kind":"keyword","text":"let"},{"text":" ","kind":"text"},{"text":"partnership","kind":"identifier"},{"kind":"text","text":": "},{"text":"ImageResource","kind":"typeIdentifier","preciseIdentifier":"s:21DeveloperToolsSupport13ImageResourceV"}],"url":"\/documentation\/volt\/developertoolssupport\/imageresource\/partnership","kind":"symbol","title":"partnership","abstract":[{"text":"The “Partnership” asset catalog image resource.","type":"text"}],"type":"topic","identifier":"doc:\/\/com.KCDev.Volt\/documentation\/Volt\/DeveloperToolsSupport\/ImageResource\/partnership","role":"symbol"},"doc://com.KCDev.Volt/documentation/Volt/DeveloperToolsSupport/ImageResource/blacksmith":{"role":"symbol","identifier":"doc:\/\/com.KCDev.Volt\/documentation\/Volt\/DeveloperToolsSupport\/ImageResource\/blacksmith","fragments":[{"kind":"keyword","text":"static"},{"text":" ","kind":"text"},{"kind":"keyword","text":"let"},{"kind":"text","text":" "},{"text":"blacksmith","kind":"identifier"},{"text":": ","kind":"text"},{"text":"ImageResource","kind":"typeIdentifier","preciseIdentifier":"s:21DeveloperToolsSupport13ImageResourceV"}],"type":"topic","url":"\/documentation\/volt\/developertoolssupport\/imageresource\/blacksmith","abstract":[{"type":"text","text":"The “Blacksmith” asset catalog image resource."}],"kind":"symbol","title":"blacksmith"},"doc://com.KCDev.Volt/documentation/Volt/DeveloperToolsSupport/ImageResource/logo1":{"role":"symbol","fragments":[{"text":"static","kind":"keyword"},{"kind":"text","text":" "},{"kind":"keyword","text":"let"},{"kind":"text","text":" "},{"kind":"identifier","text":"logo1"},{"text":": ","kind":"text"},{"preciseIdentifier":"s:21DeveloperToolsSupport13ImageResourceV","text":"ImageResource","kind":"typeIdentifier"}],"title":"logo1","identifier":"doc:\/\/com.KCDev.Volt\/documentation\/Volt\/DeveloperToolsSupport\/ImageResource\/logo1","kind":"symbol","url":"\/documentation\/volt\/developertoolssupport\/imageresource\/logo1","type":"topic","abstract":[{"type":"text","text":"The “Logo 1” asset catalog image resource."}]},"doc://com.KCDev.Volt/documentation/Volt/DeveloperToolsSupport/ImageResource/illustration4":{"abstract":[{"type":"text","text":"The “Illustration 4” asset catalog image resource."}],"kind":"symbol","role":"symbol","identifier":"doc:\/\/com.KCDev.Volt\/documentation\/Volt\/DeveloperToolsSupport\/ImageResource\/illustration4","url":"\/documentation\/volt\/developertoolssupport\/imageresource\/illustration4","title":"illustration4","fragments":[{"text":"static","kind":"keyword"},{"kind":"text","text":" "},{"text":"let","kind":"keyword"},{"kind":"text","text":" "},{"text":"illustration4","kind":"identifier"},{"text":": ","kind":"text"},{"text":"ImageResource","preciseIdentifier":"s:21DeveloperToolsSupport13ImageResourceV","kind":"typeIdentifier"}],"type":"topic"},"doc://com.KCDev.Volt/documentation/Volt/DeveloperToolsSupport/ImageResource/logoGooglePDF":{"fragments":[{"text":"static","kind":"keyword"},{"kind":"text","text":" "},{"text":"let","kind":"keyword"},{"kind":"text","text":" "},{"kind":"identifier","text":"logoGooglePDF"},{"text":": ","kind":"text"},{"text":"ImageResource","preciseIdentifier":"s:21DeveloperToolsSupport13ImageResourceV","kind":"typeIdentifier"}],"role":"symbol","abstract":[{"text":"The “Logo Google PDF” asset catalog image resource.","type":"text"}],"kind":"symbol","title":"logoGooglePDF","type":"topic","url":"\/documentation\/volt\/developertoolssupport\/imageresource\/logogooglepdf","identifier":"doc:\/\/com.KCDev.Volt\/documentation\/Volt\/DeveloperToolsSupport\/ImageResource\/logoGooglePDF"},"doc://com.KCDev.Volt/documentation/Volt/DeveloperToolsSupport/ImageResource/gloss1":{"abstract":[{"type":"text","text":"The “Gloss 1” asset catalog image resource."}],"kind":"symbol","role":"symbol","fragments":[{"kind":"keyword","text":"static"},{"text":" ","kind":"text"},{"kind":"keyword","text":"let"},{"kind":"text","text":" "},{"text":"gloss1","kind":"identifier"},{"text":": ","kind":"text"},{"text":"ImageResource","preciseIdentifier":"s:21DeveloperToolsSupport13ImageResourceV","kind":"typeIdentifier"}],"identifier":"doc:\/\/com.KCDev.Volt\/documentation\/Volt\/DeveloperToolsSupport\/ImageResource\/gloss1","type":"topic","url":"\/documentation\/volt\/developertoolssupport\/imageresource\/gloss1","title":"gloss1"},"doc://com.KCDev.Volt/documentation/Volt/DeveloperToolsSupport/ImageResource/renewables":{"role":"symbol","fragments":[{"kind":"keyword","text":"static"},{"kind":"text","text":" "},{"kind":"keyword","text":"let"},{"text":" ","kind":"text"},{"text":"renewables","kind":"identifier"},{"text":": ","kind":"text"},{"kind":"typeIdentifier","text":"ImageResource","preciseIdentifier":"s:21DeveloperToolsSupport13ImageResourceV"}],"title":"renewables","kind":"symbol","identifier":"doc:\/\/com.KCDev.Volt\/documentation\/Volt\/DeveloperToolsSupport\/ImageResource\/renewables","type":"topic","url":"\/documentation\/volt\/developertoolssupport\/imageresource\/renewables","abstract":[{"text":"The “Renewables” asset catalog image resource.","type":"text"}]},"doc://com.KCDev.Volt/documentation/Volt/DeveloperToolsSupport/ImageResource/automation":{"kind":"symbol","type":"topic","fragments":[{"text":"static","kind":"keyword"},{"kind":"text","text":" "},{"kind":"keyword","text":"let"},{"text":" ","kind":"text"},{"text":"automation","kind":"identifier"},{"text":": ","kind":"text"},{"preciseIdentifier":"s:21DeveloperToolsSupport13ImageResourceV","text":"ImageResource","kind":"typeIdentifier"}],"title":"automation","abstract":[{"type":"text","text":"The “Automation” asset catalog image resource."}],"role":"symbol","identifier":"doc:\/\/com.KCDev.Volt\/documentation\/Volt\/DeveloperToolsSupport\/ImageResource\/automation","url":"\/documentation\/volt\/developertoolssupport\/imageresource\/automation"},"doc://com.KCDev.Volt/documentation/Volt/DeveloperToolsSupport/ImageResource/cjrRenewablesLogo":{"kind":"symbol","fragments":[{"kind":"keyword","text":"static"},{"text":" ","kind":"text"},{"kind":"keyword","text":"let"},{"text":" ","kind":"text"},{"text":"cjrRenewablesLogo","kind":"identifier"},{"text":": ","kind":"text"},{"text":"ImageResource","kind":"typeIdentifier","preciseIdentifier":"s:21DeveloperToolsSupport13ImageResourceV"}],"identifier":"doc:\/\/com.KCDev.Volt\/documentation\/Volt\/DeveloperToolsSupport\/ImageResource\/cjrRenewablesLogo","type":"topic","abstract":[{"text":"The “CJR Renewables Logo” asset catalog image resource.","type":"text"}],"title":"cjrRenewablesLogo","role":"symbol","url":"\/documentation\/volt\/developertoolssupport\/imageresource\/cjrrenewableslogo"},"doc://com.KCDev.Volt/documentation/Volt/DeveloperToolsSupport/ImageResource/background9":{"type":"topic","fragments":[{"kind":"keyword","text":"static"},{"text":" ","kind":"text"},{"kind":"keyword","text":"let"},{"text":" ","kind":"text"},{"kind":"identifier","text":"background9"},{"text":": ","kind":"text"},{"kind":"typeIdentifier","preciseIdentifier":"s:21DeveloperToolsSupport13ImageResourceV","text":"ImageResource"}],"identifier":"doc:\/\/com.KCDev.Volt\/documentation\/Volt\/DeveloperToolsSupport\/ImageResource\/background9","kind":"symbol","url":"\/documentation\/volt\/developertoolssupport\/imageresource\/background9","abstract":[{"type":"text","text":"The “Background 9” asset catalog image resource."}],"role":"symbol","title":"background9"},"doc://com.KCDev.Volt/documentation/Volt/DeveloperToolsSupport/ImageResource/background1":{"role":"symbol","url":"\/documentation\/volt\/developertoolssupport\/imageresource\/background1","type":"topic","kind":"symbol","fragments":[{"text":"static","kind":"keyword"},{"text":" ","kind":"text"},{"text":"let","kind":"keyword"},{"kind":"text","text":" "},{"text":"background1","kind":"identifier"},{"kind":"text","text":": "},{"preciseIdentifier":"s:21DeveloperToolsSupport13ImageResourceV","text":"ImageResource","kind":"typeIdentifier"}],"abstract":[{"type":"text","text":"The “Background 1” asset catalog image resource."}],"identifier":"doc:\/\/com.KCDev.Volt\/documentation\/Volt\/DeveloperToolsSupport\/ImageResource\/background1","title":"background1"},"doc://com.KCDev.Volt/documentation/Volt/DeveloperToolsSupport/ImageResource/waves2":{"type":"topic","url":"\/documentation\/volt\/developertoolssupport\/imageresource\/waves2","identifier":"doc:\/\/com.KCDev.Volt\/documentation\/Volt\/DeveloperToolsSupport\/ImageResource\/waves2","role":"symbol","fragments":[{"kind":"keyword","text":"static"},{"text":" ","kind":"text"},{"text":"let","kind":"keyword"},{"kind":"text","text":" "},{"text":"waves2","kind":"identifier"},{"text":": ","kind":"text"},{"text":"ImageResource","kind":"typeIdentifier","preciseIdentifier":"s:21DeveloperToolsSupport13ImageResourceV"}],"title":"waves2","kind":"symbol","abstract":[{"type":"text","text":"The “Waves 2” asset catalog image resource."}]},"doc://com.KCDev.Volt/documentation/Volt/DeveloperToolsSupport/ImageResource/syncDataIcon":{"abstract":[{"type":"text","text":"The “Sync Data Icon” asset catalog image resource."}],"identifier":"doc:\/\/com.KCDev.Volt\/documentation\/Volt\/DeveloperToolsSupport\/ImageResource\/syncDataIcon","title":"syncDataIcon","url":"\/documentation\/volt\/developertoolssupport\/imageresource\/syncdataicon","kind":"symbol","role":"symbol","type":"topic","fragments":[{"kind":"keyword","text":"static"},{"text":" ","kind":"text"},{"text":"let","kind":"keyword"},{"text":" ","kind":"text"},{"text":"syncDataIcon","kind":"identifier"},{"text":": ","kind":"text"},{"kind":"typeIdentifier","preciseIdentifier":"s:21DeveloperToolsSupport13ImageResourceV","text":"ImageResource"}]},"doc://com.KCDev.Volt/documentation/Volt/DeveloperToolsSupport/ImageResource/background6":{"fragments":[{"kind":"keyword","text":"static"},{"kind":"text","text":" "},{"text":"let","kind":"keyword"},{"kind":"text","text":" "},{"text":"background6","kind":"identifier"},{"kind":"text","text":": "},{"text":"ImageResource","kind":"typeIdentifier","preciseIdentifier":"s:21DeveloperToolsSupport13ImageResourceV"}],"identifier":"doc:\/\/com.KCDev.Volt\/documentation\/Volt\/DeveloperToolsSupport\/ImageResource\/background6","abstract":[{"type":"text","text":"The “Background 6” asset catalog image resource."}],"url":"\/documentation\/volt\/developertoolssupport\/imageresource\/background6","kind":"symbol","type":"topic","title":"background6","role":"symbol"},"doc://com.KCDev.Volt/documentation/Volt/DeveloperToolsSupport/ImageResource/viewDocuSignIcon":{"role":"symbol","fragments":[{"text":"static","kind":"keyword"},{"text":" ","kind":"text"},{"kind":"keyword","text":"let"},{"kind":"text","text":" "},{"kind":"identifier","text":"viewDocuSignIcon"},{"kind":"text","text":": "},{"text":"ImageResource","kind":"typeIdentifier","preciseIdentifier":"s:21DeveloperToolsSupport13ImageResourceV"}],"title":"viewDocuSignIcon","kind":"symbol","identifier":"doc:\/\/com.KCDev.Volt\/documentation\/Volt\/DeveloperToolsSupport\/ImageResource\/viewDocuSignIcon","url":"\/documentation\/volt\/developertoolssupport\/imageresource\/viewdocusignicon","type":"topic","abstract":[{"type":"text","text":"The “View DocuSign Icon” asset catalog image resource."}]},"doc://com.KCDev.Volt/documentation/Volt/DeveloperToolsSupport/ImageResource/gloss2":{"title":"gloss2","kind":"symbol","type":"topic","url":"\/documentation\/volt\/developertoolssupport\/imageresource\/gloss2","fragments":[{"text":"static","kind":"keyword"},{"text":" ","kind":"text"},{"kind":"keyword","text":"let"},{"text":" ","kind":"text"},{"text":"gloss2","kind":"identifier"},{"text":": ","kind":"text"},{"preciseIdentifier":"s:21DeveloperToolsSupport13ImageResourceV","kind":"typeIdentifier","text":"ImageResource"}],"identifier":"doc:\/\/com.KCDev.Volt\/documentation\/Volt\/DeveloperToolsSupport\/ImageResource\/gloss2","abstract":[{"text":"The “Gloss 2” asset catalog image resource.","type":"text"}],"role":"symbol"},"doc://com.KCDev.Volt/documentation/Volt/DeveloperToolsSupport/ImageResource/digitalPlatform":{"role":"symbol","kind":"symbol","title":"digitalPlatform","identifier":"doc:\/\/com.KCDev.Volt\/documentation\/Volt\/DeveloperToolsSupport\/ImageResource\/digitalPlatform","type":"topic","url":"\/documentation\/volt\/developertoolssupport\/imageresource\/digitalplatform","fragments":[{"kind":"keyword","text":"static"},{"text":" ","kind":"text"},{"text":"let","kind":"keyword"},{"kind":"text","text":" "},{"text":"digitalPlatform","kind":"identifier"},{"text":": ","kind":"text"},{"preciseIdentifier":"s:21DeveloperToolsSupport13ImageResourceV","kind":"typeIdentifier","text":"ImageResource"}],"abstract":[{"type":"text","text":"The “Digital-Platform” asset catalog image resource."}]},"doc://com.KCDev.Volt/documentation/Volt/DeveloperToolsSupport/ImageResource/logoApple":{"fragments":[{"text":"static","kind":"keyword"},{"kind":"text","text":" "},{"kind":"keyword","text":"let"},{"kind":"text","text":" "},{"text":"logoApple","kind":"identifier"},{"text":": ","kind":"text"},{"kind":"typeIdentifier","preciseIdentifier":"s:21DeveloperToolsSupport13ImageResourceV","text":"ImageResource"}],"role":"symbol","abstract":[{"type":"text","text":"The “Logo Apple” asset catalog image resource."}],"url":"\/documentation\/volt\/developertoolssupport\/imageresource\/logoapple","identifier":"doc:\/\/com.KCDev.Volt\/documentation\/Volt\/DeveloperToolsSupport\/ImageResource\/logoApple","kind":"symbol","title":"logoApple","type":"topic"},"doc://com.KCDev.Volt/documentation/Volt/DeveloperToolsSupport/ImageResource/sponsor":{"fragments":[{"text":"static","kind":"keyword"},{"text":" ","kind":"text"},{"kind":"keyword","text":"let"},{"kind":"text","text":" "},{"kind":"identifier","text":"sponsor"},{"text":": ","kind":"text"},{"preciseIdentifier":"s:21DeveloperToolsSupport13ImageResourceV","kind":"typeIdentifier","text":"ImageResource"}],"abstract":[{"type":"text","text":"The “Sponsor” asset catalog image resource."}],"type":"topic","title":"sponsor","identifier":"doc:\/\/com.KCDev.Volt\/documentation\/Volt\/DeveloperToolsSupport\/ImageResource\/sponsor","role":"symbol","kind":"symbol","url":"\/documentation\/volt\/developertoolssupport\/imageresource\/sponsor"},"doc://com.KCDev.Volt/documentation/Volt/DeveloperToolsSupport/ImageResource/background2":{"type":"topic","fragments":[{"kind":"keyword","text":"static"},{"kind":"text","text":" "},{"text":"let","kind":"keyword"},{"text":" ","kind":"text"},{"kind":"identifier","text":"background2"},{"text":": ","kind":"text"},{"kind":"typeIdentifier","text":"ImageResource","preciseIdentifier":"s:21DeveloperToolsSupport13ImageResourceV"}],"url":"\/documentation\/volt\/developertoolssupport\/imageresource\/background2","kind":"symbol","role":"symbol","abstract":[{"type":"text","text":"The “Background 2” asset catalog image resource."}],"identifier":"doc:\/\/com.KCDev.Volt\/documentation\/Volt\/DeveloperToolsSupport\/ImageResource\/background2","title":"background2"},"doc://com.KCDev.Volt/documentation/Volt/DeveloperToolsSupport/ImageResource/primorisLogoBasic":{"type":"topic","role":"symbol","url":"\/documentation\/volt\/developertoolssupport\/imageresource\/primorislogobasic","kind":"symbol","fragments":[{"kind":"keyword","text":"static"},{"kind":"text","text":" "},{"kind":"keyword","text":"let"},{"text":" ","kind":"text"},{"text":"primorisLogoBasic","kind":"identifier"},{"text":": ","kind":"text"},{"kind":"typeIdentifier","preciseIdentifier":"s:21DeveloperToolsSupport13ImageResourceV","text":"ImageResource"}],"identifier":"doc:\/\/com.KCDev.Volt\/documentation\/Volt\/DeveloperToolsSupport\/ImageResource\/primorisLogoBasic","title":"primorisLogoBasic","abstract":[{"type":"text","text":"The “Primoris Logo Basic” asset catalog image resource."}]},"doc://com.KCDev.Volt/documentation/Volt/DeveloperToolsSupport/ImageResource/spark":{"fragments":[{"text":"static","kind":"keyword"},{"text":" ","kind":"text"},{"text":"let","kind":"keyword"},{"text":" ","kind":"text"},{"kind":"identifier","text":"spark"},{"kind":"text","text":": "},{"text":"ImageResource","kind":"typeIdentifier","preciseIdentifier":"s:21DeveloperToolsSupport13ImageResourceV"}],"type":"topic","abstract":[{"type":"text","text":"The “spark” asset catalog image resource."}],"url":"\/documentation\/volt\/developertoolssupport\/imageresource\/spark","role":"symbol","kind":"symbol","identifier":"doc:\/\/com.KCDev.Volt\/documentation\/Volt\/DeveloperToolsSupport\/ImageResource\/spark","title":"spark"},"doc://com.KCDev.Volt/documentation/Volt/DeveloperToolsSupport/ImageResource/blob1":{"role":"symbol","fragments":[{"text":"static","kind":"keyword"},{"kind":"text","text":" "},{"kind":"keyword","text":"let"},{"kind":"text","text":" "},{"kind":"identifier","text":"blob1"},{"text":": ","kind":"text"},{"preciseIdentifier":"s:21DeveloperToolsSupport13ImageResourceV","text":"ImageResource","kind":"typeIdentifier"}],"title":"blob1","identifier":"doc:\/\/com.KCDev.Volt\/documentation\/Volt\/DeveloperToolsSupport\/ImageResource\/blob1","kind":"symbol","url":"\/documentation\/volt\/developertoolssupport\/imageresource\/blob1","type":"topic","abstract":[{"type":"text","text":"The “Blob 1” asset catalog image resource."}]},"doc://com.KCDev.Volt/documentation/Volt/DeveloperToolsSupport/ImageResource/economy":{"identifier":"doc:\/\/com.KCDev.Volt\/documentation\/Volt\/DeveloperToolsSupport\/ImageResource\/economy","url":"\/documentation\/volt\/developertoolssupport\/imageresource\/economy","role":"symbol","fragments":[{"text":"static","kind":"keyword"},{"text":" ","kind":"text"},{"kind":"keyword","text":"let"},{"kind":"text","text":" "},{"kind":"identifier","text":"economy"},{"kind":"text","text":": "},{"text":"ImageResource","kind":"typeIdentifier","preciseIdentifier":"s:21DeveloperToolsSupport13ImageResourceV"}],"kind":"symbol","title":"economy","type":"topic","abstract":[{"type":"text","text":"The “Economy” asset catalog image resource."}]},"doc://com.KCDev.Volt/documentation/Volt/DeveloperToolsSupport/ImageResource/logoEmail":{"kind":"symbol","title":"logoEmail","fragments":[{"text":"static","kind":"keyword"},{"text":" ","kind":"text"},{"text":"let","kind":"keyword"},{"text":" ","kind":"text"},{"kind":"identifier","text":"logoEmail"},{"kind":"text","text":": "},{"preciseIdentifier":"s:21DeveloperToolsSupport13ImageResourceV","text":"ImageResource","kind":"typeIdentifier"}],"identifier":"doc:\/\/com.KCDev.Volt\/documentation\/Volt\/DeveloperToolsSupport\/ImageResource\/logoEmail","url":"\/documentation\/volt\/developertoolssupport\/imageresource\/logoemail","type":"topic","abstract":[{"text":"The “Logo Email” asset catalog image resource.","type":"text"}],"role":"symbol"},"doc://com.KCDev.Volt/documentation/Volt/DeveloperToolsSupport/ImageResource/illustration11":{"fragments":[{"text":"static","kind":"keyword"},{"kind":"text","text":" "},{"kind":"keyword","text":"let"},{"kind":"text","text":" "},{"kind":"identifier","text":"illustration11"},{"text":": ","kind":"text"},{"preciseIdentifier":"s:21DeveloperToolsSupport13ImageResourceV","text":"ImageResource","kind":"typeIdentifier"}],"url":"\/documentation\/volt\/developertoolssupport\/imageresource\/illustration11","identifier":"doc:\/\/com.KCDev.Volt\/documentation\/Volt\/DeveloperToolsSupport\/ImageResource\/illustration11","abstract":[{"type":"text","text":"The “Illustration 11” asset catalog image resource."}],"kind":"symbol","type":"topic","title":"illustration11","role":"symbol"},"doc://com.KCDev.Volt/documentation/Volt/DeveloperToolsSupport/ImageResource/illustration1":{"identifier":"doc:\/\/com.KCDev.Volt\/documentation\/Volt\/DeveloperToolsSupport\/ImageResource\/illustration1","kind":"symbol","abstract":[{"type":"text","text":"The “Illustration 1” asset catalog image resource."}],"type":"topic","role":"symbol","fragments":[{"text":"static","kind":"keyword"},{"text":" ","kind":"text"},{"text":"let","kind":"keyword"},{"text":" ","kind":"text"},{"kind":"identifier","text":"illustration1"},{"text":": ","kind":"text"},{"text":"ImageResource","kind":"typeIdentifier","preciseIdentifier":"s:21DeveloperToolsSupport13ImageResourceV"}],"url":"\/documentation\/volt\/developertoolssupport\/imageresource\/illustration1","title":"illustration1"},"doc://com.KCDev.Volt/documentation/Volt/DeveloperToolsSupport/ImageResource/capitolHill":{"url":"\/documentation\/volt\/developertoolssupport\/imageresource\/capitolhill","fragments":[{"kind":"keyword","text":"static"},{"text":" ","kind":"text"},{"kind":"keyword","text":"let"},{"kind":"text","text":" "},{"text":"capitolHill","kind":"identifier"},{"text":": ","kind":"text"},{"kind":"typeIdentifier","preciseIdentifier":"s:21DeveloperToolsSupport13ImageResourceV","text":"ImageResource"}],"kind":"symbol","role":"symbol","type":"topic","title":"capitolHill","abstract":[{"type":"text","text":"The “Capitol-Hill” asset catalog image resource."}],"identifier":"doc:\/\/com.KCDev.Volt\/documentation\/Volt\/DeveloperToolsSupport\/ImageResource\/capitolHill"},"doc://com.KCDev.Volt/documentation/Volt/DeveloperToolsSupport/ImageResource/primorisLogoWhite":{"kind":"symbol","role":"symbol","type":"topic","title":"primorisLogoWhite","abstract":[{"text":"The “Primoris Logo White” asset catalog image resource.","type":"text"}],"url":"\/documentation\/volt\/developertoolssupport\/imageresource\/primorislogowhite","identifier":"doc:\/\/com.KCDev.Volt\/documentation\/Volt\/DeveloperToolsSupport\/ImageResource\/primorisLogoWhite","fragments":[{"text":"static","kind":"keyword"},{"text":" ","kind":"text"},{"kind":"keyword","text":"let"},{"kind":"text","text":" "},{"text":"primorisLogoWhite","kind":"identifier"},{"kind":"text","text":": "},{"kind":"typeIdentifier","preciseIdentifier":"s:21DeveloperToolsSupport13ImageResourceV","text":"ImageResource"}]},"doc://com.KCDev.Volt/documentation/Volt/DeveloperToolsSupport/ImageResource/background7":{"url":"\/documentation\/volt\/developertoolssupport\/imageresource\/background7","kind":"symbol","type":"topic","role":"symbol","identifier":"doc:\/\/com.KCDev.Volt\/documentation\/Volt\/DeveloperToolsSupport\/ImageResource\/background7","abstract":[{"text":"The “Background 7” asset catalog image resource.","type":"text"}],"fragments":[{"text":"static","kind":"keyword"},{"kind":"text","text":" "},{"text":"let","kind":"keyword"},{"kind":"text","text":" "},{"kind":"identifier","text":"background7"},{"kind":"text","text":": "},{"kind":"typeIdentifier","preciseIdentifier":"s:21DeveloperToolsSupport13ImageResourceV","text":"ImageResource"}],"title":"background7"},"doc://com.KCDev.Volt/documentation/Volt/DeveloperToolsSupport":{"kind":"symbol","abstract":[],"url":"\/documentation\/volt\/developertoolssupport","type":"topic","title":"DeveloperToolsSupport","identifier":"doc:\/\/com.KCDev.Volt\/documentation\/Volt\/DeveloperToolsSupport","role":"collection"},"doc://com.KCDev.Volt/documentation/Volt/DeveloperToolsSupport/ImageResource/global":{"fragments":[{"text":"static","kind":"keyword"},{"text":" ","kind":"text"},{"kind":"keyword","text":"let"},{"kind":"text","text":" "},{"kind":"identifier","text":"global"},{"kind":"text","text":": "},{"text":"ImageResource","kind":"typeIdentifier","preciseIdentifier":"s:21DeveloperToolsSupport13ImageResourceV"}],"url":"\/documentation\/volt\/developertoolssupport\/imageresource\/global","identifier":"doc:\/\/com.KCDev.Volt\/documentation\/Volt\/DeveloperToolsSupport\/ImageResource\/global","type":"topic","kind":"symbol","abstract":[{"type":"text","text":"The “Global” asset catalog image resource."}],"title":"global","role":"symbol"},"doc://com.KCDev.Volt/documentation/Volt/DeveloperToolsSupport/ImageResource/logo2":{"abstract":[{"type":"text","text":"The “Logo 2” asset catalog image resource."}],"type":"topic","identifier":"doc:\/\/com.KCDev.Volt\/documentation\/Volt\/DeveloperToolsSupport\/ImageResource\/logo2","role":"symbol","url":"\/documentation\/volt\/developertoolssupport\/imageresource\/logo2","title":"logo2","fragments":[{"kind":"keyword","text":"static"},{"text":" ","kind":"text"},{"text":"let","kind":"keyword"},{"text":" ","kind":"text"},{"text":"logo2","kind":"identifier"},{"text":": ","kind":"text"},{"kind":"typeIdentifier","preciseIdentifier":"s:21DeveloperToolsSupport13ImageResourceV","text":"ImageResource"}],"kind":"symbol"},"doc://com.KCDev.Volt/documentation/Volt/DeveloperToolsSupport/ImageResource/logo3":{"identifier":"doc:\/\/com.KCDev.Volt\/documentation\/Volt\/DeveloperToolsSupport\/ImageResource\/logo3","fragments":[{"kind":"keyword","text":"static"},{"kind":"text","text":" "},{"kind":"keyword","text":"let"},{"kind":"text","text":" "},{"kind":"identifier","text":"logo3"},{"kind":"text","text":": "},{"preciseIdentifier":"s:21DeveloperToolsSupport13ImageResourceV","text":"ImageResource","kind":"typeIdentifier"}],"kind":"symbol","type":"topic","title":"logo3","abstract":[{"type":"text","text":"The “Logo 3” asset catalog image resource."}],"role":"symbol","url":"\/documentation\/volt\/developertoolssupport\/imageresource\/logo3"},"doc://com.KCDev.Volt/documentation/Volt/DeveloperToolsSupport/ImageResource/logoGoogle":{"identifier":"doc:\/\/com.KCDev.Volt\/documentation\/Volt\/DeveloperToolsSupport\/ImageResource\/logoGoogle","title":"logoGoogle","role":"symbol","abstract":[{"type":"text","text":"The “Logo Google” asset catalog image resource."}],"fragments":[{"text":"static","kind":"keyword"},{"text":" ","kind":"text"},{"kind":"keyword","text":"let"},{"text":" ","kind":"text"},{"text":"logoGoogle","kind":"identifier"},{"kind":"text","text":": "},{"kind":"typeIdentifier","preciseIdentifier":"s:21DeveloperToolsSupport13ImageResourceV","text":"ImageResource"}],"url":"\/documentation\/volt\/developertoolssupport\/imageresource\/logogoogle","type":"topic","kind":"symbol"},"doc://com.KCDev.Volt/documentation/Volt/DeveloperToolsSupport/ImageResource/acsLogo":{"title":"acsLogo","type":"topic","url":"\/documentation\/volt\/developertoolssupport\/imageresource\/acslogo","identifier":"doc:\/\/com.KCDev.Volt\/documentation\/Volt\/DeveloperToolsSupport\/ImageResource\/acsLogo","kind":"symbol","abstract":[{"text":"The “ACS Logo” asset catalog image resource.","type":"text"}],"role":"symbol","fragments":[{"kind":"keyword","text":"static"},{"kind":"text","text":" "},{"kind":"keyword","text":"let"},{"kind":"text","text":" "},{"kind":"identifier","text":"acsLogo"},{"kind":"text","text":": "},{"text":"ImageResource","kind":"typeIdentifier","preciseIdentifier":"s:21DeveloperToolsSupport13ImageResourceV"}]},"doc://com.KCDev.Volt/documentation/Volt/DeveloperToolsSupport/ImageResource/newEnrollmentIcon":{"role":"symbol","fragments":[{"text":"static","kind":"keyword"},{"text":" ","kind":"text"},{"kind":"keyword","text":"let"},{"kind":"text","text":" "},{"kind":"identifier","text":"newEnrollmentIcon"},{"text":": ","kind":"text"},{"kind":"typeIdentifier","text":"ImageResource","preciseIdentifier":"s:21DeveloperToolsSupport13ImageResourceV"}],"abstract":[{"text":"The “New Enrollment Icon” asset catalog image resource.","type":"text"}],"title":"newEnrollmentIcon","identifier":"doc:\/\/com.KCDev.Volt\/documentation\/Volt\/DeveloperToolsSupport\/ImageResource\/newEnrollmentIcon","url":"\/documentation\/volt\/developertoolssupport\/imageresource\/newenrollmenticon","kind":"symbol","type":"topic"},"doc://com.KCDev.Volt/documentation/Volt/DeveloperToolsSupport/ImageResource/apprentice":{"identifier":"doc:\/\/com.KCDev.Volt\/documentation\/Volt\/DeveloperToolsSupport\/ImageResource\/apprentice","kind":"symbol","role":"symbol","title":"apprentice","fragments":[{"text":"static","kind":"keyword"},{"text":" ","kind":"text"},{"text":"let","kind":"keyword"},{"text":" ","kind":"text"},{"kind":"identifier","text":"apprentice"},{"text":": ","kind":"text"},{"kind":"typeIdentifier","preciseIdentifier":"s:21DeveloperToolsSupport13ImageResourceV","text":"ImageResource"}],"url":"\/documentation\/volt\/developertoolssupport\/imageresource\/apprentice","abstract":[{"text":"The “Apprentice” asset catalog image resource.","type":"text"}],"type":"topic"},"doc://com.KCDev.Volt/documentation/Volt/DeveloperToolsSupport/ImageResource/logo4":{"url":"\/documentation\/volt\/developertoolssupport\/imageresource\/logo4","title":"logo4","kind":"symbol","identifier":"doc:\/\/com.KCDev.Volt\/documentation\/Volt\/DeveloperToolsSupport\/ImageResource\/logo4","type":"topic","role":"symbol","fragments":[{"text":"static","kind":"keyword"},{"text":" ","kind":"text"},{"text":"let","kind":"keyword"},{"text":" ","kind":"text"},{"text":"logo4","kind":"identifier"},{"text":": ","kind":"text"},{"preciseIdentifier":"s:21DeveloperToolsSupport13ImageResourceV","text":"ImageResource","kind":"typeIdentifier"}],"abstract":[{"type":"text","text":"The “Logo 4” asset catalog image resource."}]}}}